chili/__init__.py
chili/__version__.py
chili/decoder.py
chili/encoder.py
chili/error.py
chili/iso_datetime.py
chili/json_support.py
chili/mapper.py
chili/py.typed
chili/serializer.py
chili/state.py
chili/typing.py
chili-2.9.0.dist-info/LICENSE
chili-2.9.0.dist-info/METADATA
chili-2.9.0.dist-info/WHEEL
chili-2.9.0.dist-info/RECORD
