Metadata-Version: 2.1
Name: chili
Version: 2.9.0
Summary: Chili is serialisation library. It can serialise/deserialise almost any object.
Home-page: https://github.com/kodemore/chili
License: MIT
Keywords: class,decode,deserialise,encode,object,serialise
Author: Dawid Kraczkowski
Author-email: dawid.kraczkowski@gmail.com
Requires-Python: >=3.8,<4.0
Classifier: Development Status :: 5 - Production/Stable
Classifier: Intended Audience :: Developers
Classifier: License :: OSI Approved :: MIT License
Classifier: Natural Language :: English
Classifier: Programming Language :: Python
Classifier: Programming Language :: Python :: 3
Classifier: Programming Language :: Python :: 3.8
Classifier: Programming Language :: Python :: 3.9
Classifier: Programming Language :: Python :: 3.10
Classifier: Programming Language :: Python :: 3.11
Classifier: Programming Language :: Python :: 3.12
Classifier: Topic :: Software Development :: Code Generators
Classifier: Topic :: Software Development :: Libraries
Classifier: Topic :: Software Development :: Libraries :: Python Modules
Classifier: Topic :: Utilities
Requires-Dist: gaffe (>=0.3.0)
Requires-Dist: typing-extensions (>=4.2,<5.0)
Project-URL: Documentation, https://github.com/kodemore/chili
Project-URL: Repository, https://github.com/kodemore/chili
